{"cameraMode":{"drawMode":0,"name":"Shaded","section":"Shading Mode"},"sceneLighting":false,"audioPlay":false,"sceneViewState":{"showFog":true,"showMaterialUpdate":false,"showSkybox":false,"showFlares":true,"showImageEffects":true,"showParticleSystems":true},"in2DMode":false,"pivot":{"x":-12.077006340026856,"y":-12.815204620361329,"z":-10.80823802947998},"rotation":{"x":0.1404084861278534,"y":-0.8580467700958252,"z":0.32034143805503847,"w":0.3761078417301178},"size":24.714584350585939,"orthographic":false}